CHANGES.rst
CONTRIBUTORS.rst
MANIFEST.in
README.rst
setup.cfg
setup.py
docs/LICENSE.GPL
docs/LICENSE.txt
src/collective/__init__.py
src/collective.portlet.twitter.egg-info/PKG-INFO
src/collective.portlet.twitter.egg-info/SOURCES.txt
src/collective.portlet.twitter.egg-info/dependency_links.txt
src/collective.portlet.twitter.egg-info/entry_points.txt
src/collective.portlet.twitter.egg-info/namespace_packages.txt
src/collective.portlet.twitter.egg-info/not-zip-safe
src/collective.portlet.twitter.egg-info/requires.txt
src/collective.portlet.twitter.egg-info/top_level.txt
src/collective/portlet/__init__.py
src/collective/portlet/twitter/__init__.py
src/collective/portlet/twitter/config.py
src/collective/portlet/twitter/configure.zcml
src/collective/portlet/twitter/interfaces.py
src/collective/portlet/twitter/new.pt
src/collective/portlet/twitter/new.py
src/collective/portlet/twitter/setuphandlers.py
src/collective/portlet/twitter/testing.py
src/collective/portlet/twitter/profiles/default/browserlayer.xml
src/collective/portlet/twitter/profiles/default/collective.twitter.widget_various.txt
src/collective/portlet/twitter/profiles/default/import_steps.xml
src/collective/portlet/twitter/profiles/default/metadata.xml
src/collective/portlet/twitter/profiles/default/portlets.xml
src/collective/portlet/twitter/tests/__init__.py
src/collective/portlet/twitter/tests/test_setup.py
src/collective/portlet/twitter/tests/test_widget_new.py