Metadata-Version: 1.1
Name: collective.portlet.twitter
Version: 1.0b3
Summary: Twitter Widget Portlet - https://twitter.com/settings/widgets
Home-page: https://github.com/collective/collective.portlet.twitter
Author: Thiago Avelino
Author-email: thiagoavelinoster@gmail.com
License: GPLv2
Keywords: plone portlet twitter widget
Platform: UNKNOWN
Classifier: Development Status :: 4 - Beta
Classifier: Environment :: Web Environment
Classifier: Framework :: Plone
Classifier: Framework :: Plone :: 4.1
Classifier: Framework :: Plone :: 4.2
Classifier: Framework :: Plone :: 4.3
Classifier: Intended Audience :: System Administrators
Classifier: License :: OSI Approved :: GNU General Public License v2 (GPLv2)
Classifier: Operating System :: OS Independent
Classifier: Programming Language :: JavaScript
Classifier: Programming Language :: Python
Classifier: Programming Language :: Python :: 2.6
Classifier: Programming Language :: Python :: 2.7
Classifier: Topic :: Software Development :: Libraries :: Python Modules
